README.txt
setup.py
sistdmyy/__init__.py
sistdmyy/_version.py
sistdmyy/base.py
sistdmyy/futian.py
sistdmyy.egg-info/PKG-INFO
sistdmyy.egg-info/SOURCES.txt
sistdmyy.egg-info/dependency_links.txt
sistdmyy.egg-info/requires.txt
sistdmyy.egg-info/top_level.txt
sistdmyy/dz/__init__.py
sistdmyy/dz/dz_jd.py
sistdmyy/dz/dz_std.py