Metadata-Version: 1.1
Name: sistdmyy
Version: 1.3.1
Summary: 兰孟飞在深圳标准技术研究部的工作
Home-page: https://user.qzone.qq.com/865377886
Author: lanmengfei
Author-email: 865377886@qq.com
License: MIT
Platform: UNKNOWN
Classifier: Environment :: Web Environment
Classifier: Intended Audience :: Developers
Classifier: Operating System :: OS Independent
Classifier: Topic :: Text Processing :: Indexing
Classifier: Topic :: Utilities
Classifier: Topic :: Internet
Classifier: Topic :: Software Development :: Libraries :: Python Modules
Classifier: Programming Language :: Python
Classifier: Programming Language :: Python :: 3
